rubin_lc_simulator/__init__.py
rubin_lc_simulator/config.py
rubin_lc_simulator/lightcurves.py
rubin_lc_simulator/simulator.py
rubin_lc_simulator-1.12.dist-info/licenses/LICENSE
rubin_lc_simulator-1.12.dist-info/METADATA
rubin_lc_simulator-1.12.dist-info/WHEEL
rubin_lc_simulator-1.12.dist-info/top_level.txt
rubin_lc_simulator-1.12.dist-info/RECORD
