Metadata-Version: 2.4
Name: rubin-lc-simulator
Version: 1.12
Summary: Open-source tool to simulate LSST light curves with Rubin cadence and per-epoch noise.
Home-page: https://github.com/Professor-G/rubin-lc-simulator
Author: Daniel Godines
Author-email: Daniel Godines <danielgodinez123@gmail.com>
License: MIT
Requires-Python: >=3.7
License-File: LICENSE
Requires-Dist: numpy
Dynamic: author
Dynamic: home-page
Dynamic: license-file
Dynamic: requires-python
